pyenvsearch/__init__.py
pyenvsearch/__main__.py
pyenvsearch/main.py
pyenvsearch/core/__init__.py
pyenvsearch/core/docs.py
pyenvsearch/core/llm.py
pyenvsearch/core/packages.py
pyenvsearch/core/search.py
pyenvsearch/core/venv.py
pyenvsearch-0.4.0.dist-info/METADATA
pyenvsearch-0.4.0.dist-info/WHEEL
pyenvsearch-0.4.0.dist-info/entry_points.txt
pyenvsearch-0.4.0.dist-info/licenses/LICENSE
pyenvsearch-0.4.0.dist-info/RECORD
