Metadata-Version: 2.4
Name: pyenvsearch
Version: 0.4.0
Summary: Python library navigation and AI-powered analysis tool for developers and AI agents. Combines traditional code search with LLM-powered package insights.
Project-URL: Homepage, https://github.com/mjbommar/pyenvsearch
Project-URL: Repository, https://github.com/mjbommar/pyenvsearch.git
Project-URL: Issues, https://github.com/mjbommar/pyenvsearch/issues
Project-URL: Documentation, https://github.com/mjbommar/pyenvsearch#readme
Project-URL: Changelog, https://github.com/mjbommar/pyenvsearch/releases
Author-email: Michael Bommarito <michael.bommarito@gmail.com>
License: MIT
License-File: LICENSE
Keywords: ai,development,documentation,llm,navigation,packages,python,search,uv,uvx,virtual-environment
Classifier: Development Status :: 4 - Beta
Classifier: Intended Audience :: Developers
Classifier: License :: OSI Approved :: MIT License
Classifier: Programming Language :: Python :: 3
Classifier: Programming Language :: Python :: 3.12
Classifier: Programming Language :: Python :: 3.13
Classifier: Programming Language :: Python :: 3.14
Classifier: Topic :: Software Development :: Documentation
Classifier: Topic :: Software Development :: Libraries :: Python Modules
Classifier: Topic :: Utilities
Requires-Python: >=3.12
Provides-Extra: all
Requires-Dist: ast-grep-cli>=0.39.4; extra == 'all'
Requires-Dist: ripgrep>=14.1.0; extra == 'all'
Provides-Extra: dev
Requires-Dist: pytest-asyncio>=0.21; extra == 'dev'
Requires-Dist: pytest-cov>=4.0; extra == 'dev'
Requires-Dist: pytest>=7.0; extra == 'dev'
Provides-Extra: performance
Requires-Dist: ast-grep-cli>=0.39.4; extra == 'performance'
Requires-Dist: ripgrep>=14.1.0; extra == 'performance'
